ZiTokenizer/He2Zi.py
ZiTokenizer/UnicodeTokenizer.py
ZiTokenizer/ZiCutter.py
ZiTokenizer/ZiSegmenter.py
ZiTokenizer/ZiTokenizer.py
ZiTokenizer/__init__.py
ZiTokenizer-0.0.8.dist-info/METADATA
ZiTokenizer-0.0.8.dist-info/WHEEL
ZiTokenizer-0.0.8.dist-info/top_level.txt
ZiTokenizer-0.0.8.dist-info/RECORD
