Metadata-Version: 2.1
Name: ZiTokenizer
Version: 0.0.8
Summary: ZiTokenizer: tokenize world text as Zi
Home-page: https://github.com/laohur/ZiCutter
Author: laohur
Author-email: laohur@gmail.com
License: [Anti-996 License](https: // github.com/996icu/996.ICU/blob/master/LICENSE)
Keywords: UnicodeTokenizer,ZiCutter,ZiTokenizer,Tokenizer,Unicode,laohur
Requires-Python: >=3.0
Requires-Dist: logzero
Requires-Dist: pyahocorasick
